{
  "users": [
    {
      "id": "a52b",
      "name": "Agnieszka Draganczyk",
      "day": "23",
      "month": "1",
      "year": "1988",
      "email": "agnieszka.127@interia.pl",
      "password": "ddd"
    },
    {
      "id": "e454",
      "name": "Agnieszka Draganczyk",
      "day": "23",
      "month": "1",
      "year": "1988",
      "email": "agnieszka.127@interia.pl",
      "password": "dfgdhdhfg"
    },
    {
      "id": "e9c3",
      "name": "Agnieszka Draganczyk",
      "day": "23",
      "month": "1",
      "year": "1988",
      "email": "agnieszka.127@interia.pl",
      "password": "234555"
    },
    {
      "id": "6e66"
    },
    {
      "id": "",
      "name": "",
      "day": "",
      "month": "",
      "year": "",
      "email": "",
      "password": ""
    },
    {
      "id": "99d3",
      "name": "Agnieszka Draganczyk",
      "day": "23",
      "month": "1",
      "year": "1988",
      "email": "agnieszka.127@interia.pl",
      "password": "234567"
    },
    {
      "id": "e537",
      "name": "",
      "day": "",
      "month": "1",
      "year": "",
      "email": "",
      "password": ""
    },
    {
      "id": "5a3c",
      "name": "Agnieszka Draganczyk",
      "day": "4",
      "month": "1",
      "year": "1980",
      "email": "agnieszka.127@interia.pl",
      "password": "werty"
    },
    {
      "id": "ed64",
      "name": "Agnieszka Draganczyk",
      "day": "4",
      "month": "1",
      "year": "1980",
      "email": "agnieszka.125@interia.pl",
      "password": "wer"
    },
    {
      "id": "3c86",
      "name": "Agnieszka Draganczyk",
      "day": "4",
      "month": "1",
      "year": "1980",
      "email": "agnieszka.120@interia.pl",
      "password": "ola"
    },
    {
      "id": "7d53",
      "name": "Ala",
      "day": "1",
      "month": "1",
      "year": "1990",
      "email": "ala.123@gmail.com",
      "password": "ala"
    },
    {
      "id": "3141",
      "name": "Agnieszka Draganczyk",
      "day": "3",
      "month": "1",
      "year": "1990",
      "email": "agnieszka.127@interia.pl",
      "password": "monika"
    },
    {
      "id": "ca37",
      "name": "Agnieszka Draganczyk",
      "day": "3",
      "month": "1",
      "year": "1990",
      "email": "agnieszka.127@interia.pl",
      "password": "2a5de9a3a0c5c8749a90ad51c994991354aef84ed18cf4352333261f2a233742"
    },
    {
      "id": "ca09",
      "name": "Agnieszka Draganczyk",
      "day": "3",
      "month": "1",
      "year": "1990",
      "email": "agnieszka.127@interia.pl",
      "password": "c393e323121f6846f349cc714a07c0dca605963bb4d65c799ffb1e2a11699e57"
    },
    {
      "id": "d4c9",
      "name": "Agnieszka Draganczyk",
      "day": "3",
      "month": "1",
      "year": "1990",
      "email": "agnieszka.127@interia.pl",
      "password": "df0492b9b264441832d8a3fc4a4334ffe01545f5f399b093f545fed15cca2796"
    },
    {
      "id": "d080",
      "name": "Agnieszka Draganczyk",
      "day": "3",
      "month": "1",
      "year": "1990",
      "email": "agnieszka.127@interia.pl",
      "password": "750282c522c3a724e173f53a2e6c431b927e2c30cff9b138d07fa1083551b2e1"
    },
    {
      "id": "e459",
      "name": "Agnieszka Draganczyk",
      "day": "3",
      "month": "1",
      "year": "1990",
      "email": "agnieszka.127@interia.pl",
      "password": "824162b690a30e10baf1ba76d567bf2414cc02a3329dfdba235140adef35a71c"
    }
  ]
}